bamboos/__init__.py
bamboos/analysis.py
bamboos/benchmark.py
bamboos/color.py
bamboos/date.py
bamboos/encode.py
bamboos/ensemble.py
bamboos/explain.py
bamboos/explore.py
bamboos/io.py
bamboos/logger.py
bamboos/metric.py
bamboos/prepare.py
bamboos/select.py
bamboos/tune.py
bamboos/visualize.py
bamboos/utils/__init__.py
bamboos/utils/dataframe.py
bamboos/utils/dates.py
bamboos/utils/format.py
bamboos/utils/model/__init__.py
bamboos/utils/model/base_model.py
bamboos/utils/model/ligthgbm_model.py
bamboos/utils/model/model_zoo.py
bamboos/utils/model/param_zoo.py
bamboos/utils/model/sklearn_model.py
bamboos/utils/model/xgboost_model.py
bamboos-0.2.0.dist-info/LICENSE
bamboos-0.2.0.dist-info/WHEEL
bamboos-0.2.0.dist-info/METADATA
bamboos-0.2.0.dist-info/RECORD
