Metadata-Version: 2.1
Name: bamboos
Version: 0.2.0
Summary: Wrapper Functions for pandas, numpy, and scikit learn
Home-page: http://github.com/AdityaSidharta/bamboos
License: UNKNOWN
Author: Aditya Kelvianto Sidharta
Author-email: aditya.sdrt@gmail.com
Classifier: License :: OSI Approved :: MIT License
Classifier: Development Status :: 1 - Planning
Classifier: Programming Language :: Python :: 3 :: Only
Requires-Dist: numpy
Requires-Dist: pandas
Requires-Dist: scikit-learn
Requires-Dist: matplotlib
Requires-Dist: seaborn
Requires-Dist: lightgbm
Requires-Dist: seaborn
Requires-Dist: category_encoders>=2.0.0
Requires-Dist: matplotlib-venn
